LICENSE
MANIFEST.in
README.rst
setup.py
django_user_report.egg-info/PKG-INFO
django_user_report.egg-info/SOURCES.txt
django_user_report.egg-info/dependency_links.txt
django_user_report.egg-info/requires.txt
django_user_report.egg-info/top_level.txt
report_system/__init__.py
report_system/admin.py
report_system/apps.py
report_system/conf.py
report_system/managers.py
report_system/models.py
report_system/serializers.py
report_system/tests.py
report_system/urls.py
report_system/utils.py
report_system/views.py
report_system/signals/__init__.py
report_system/signals/handlers.py
report_system/signals/signals.py
report_system/templates/report_system/email/report_notice_message.txt
report_system/templates/report_system/email/report_notice_subject.txt