Metadata-Version: 1.1
Name: django-user-report
Version: 1.0.2
Summary: A simple user content report system with RESTful api and Email Notification.
Home-page: https://github.com/DrChai/django-user-report
Author: Edward Chai
Author-email: edwardc@acrossor.com
License: MIT License
Platform: UNKNOWN
Classifier: Environment :: Web Environment
Classifier: Framework :: Django
Classifier: Intended Audience :: Developers
Classifier: License :: OSI Approved :: MIT License
Classifier: Operating System :: OS Independent
Classifier: Programming Language :: Python
Classifier: Programming Language :: Python :: 2
Classifier: Programming Language :: Python :: 3
Classifier: Intended Audience :: Developers
Classifier: Intended Audience :: System Administrators
Classifier: Operating System :: OS Independent
Classifier: Topic :: Software Development
